pyvindex/__init__.py
pyvindex/pyvindex.py
pyvindex-0.0.2.dist-info/LICENSE
pyvindex-0.0.2.dist-info/METADATA
pyvindex-0.0.2.dist-info/WHEEL
pyvindex-0.0.2.dist-info/top_level.txt
pyvindex-0.0.2.dist-info/RECORD
